topsis/__init__.py
topsis/topsis.py
topsis_102303066-0.1.0.dist-info/licenses/LICENSE
topsis_102303066-0.1.0.dist-info/METADATA
topsis_102303066-0.1.0.dist-info/WHEEL
topsis_102303066-0.1.0.dist-info/top_level.txt
topsis_102303066-0.1.0.dist-info/RECORD
